proton/__init__.py
proton/app.py
proton/core/__init__.py
proton/core/errors.py
proton/core/run_manager.py
proton/db/__init__.py
proton/db/db.py
proton/db/model.py
proton/db/types.py
proton/handler/__init__.py
proton/handler/request.py
proton/handler/response.py
proton/handler/router.py
proton/handler/status.py
proton/utils/__init__.py
proton/utils/datastructures.py
proton/utils/logger.py
proton/utils/route_parser.py
proton/utils/tools.py
test/__init__.py
test/controllers.py
test/models.py
test/routes.py
void_proton-0.1.0.dist-info/LICENSE
void_proton-0.1.0.dist-info/METADATA
void_proton-0.1.0.dist-info/WHEEL
void_proton-0.1.0.dist-info/top_level.txt
void_proton-0.1.0.dist-info/RECORD
