Metadata-Version: 2.1
Name: void-proton
Version: 0.1.0
Summary: A proton sized python framework for building backend web applications
Home-page: https://github.com/Nandan-unni/proton-py
Author: Nandanunni A S
Author-email: asnqln@gmail.com
License: MIT
Platform: UNKNOWN
Classifier: License :: OSI Approved :: MIT License
Classifier: Programming Language :: Python :: 3
Classifier: Programming Language :: Python :: 3.7
Classifier: Operating System :: OS Independent
Requires-Python: >=3.6
License-File: LICENSE
Requires-Dist: gunicorn (==20.0.4)
Requires-Dist: colorama (==0.4.4)
